ducktype/__init__.py
ducktype/entities.py
mallard/__init__.py
mallard/ducktype/__init__.py
mallard/ducktype/entities.py
mallard/ducktype/parser.py
mallard/ducktype/extensions/__init__.py
mallard/ducktype/extensions/_test.py
mallard/ducktype/extensions/csv.py
mallard/ducktype/extensions/docbook.py
mallard/ducktype/extensions/if.py
mallard_ducktype-1.0.2.data/scripts/ducktype
mallard_ducktype-1.0.2.dist-info/AUTHORS
mallard_ducktype-1.0.2.dist-info/COPYING
mallard_ducktype-1.0.2.dist-info/METADATA
mallard_ducktype-1.0.2.dist-info/WHEEL
mallard_ducktype-1.0.2.dist-info/pbr.json
mallard_ducktype-1.0.2.dist-info/top_level.txt
mallard_ducktype-1.0.2.dist-info/RECORD
